{
  "a": ["ア", "ァ"],
  "b": ["", "ㇷ゙"],
  "bb": ["", "ㇷ゙˙"],
  "ba": ["バ"],
  "bi": ["ビ"],
  "bu": ["ブ"],
  "be": ["ベ"],
  "bo": ["ボ"],
  "ca": ["サ̣̅"],
  "ci": ["チ̣"],
  "cu": ["ツ̣"],
  "ce": ["セ̣̅"],
  "co": ["ソ̣̅"],
  "cha": ["サ̅"],
  "chi": ["チ"],
  "chu": ["ツ"],
  "che": ["セ̅"],
  "cho": ["ソ̅"],
  "e": ["エ", "ェ"],
  "er": [""],
  "f": ["ˉ", "ˉ~"],
  "g": ["", "ㇰ゙"],
  "gg": ["", "ㇰ゙˙"],
  "ga": ["ガ"],
  "gi": ["ギ"],
  "gu": ["グ"],
  "ge": ["ゲ"],
  "go": ["ゴ"],
  "h": ["", "ㇷ", "ㇷ~"],
  "hh": ["", "ㇷ˙", "ㇷ˙~"],
  "ha": ["ハ"],
  "hi": ["ヒ"],
  "hu": ["フ"],
  "he": ["ヘ"],
  "ho": ["ホ"],
  "i": ["イ", "ィ"],
  "ir": ["ウ̅", "ゥ̅"],
  "j": ["", "ㇲ゙"],
  "jj": ["", "ㇲ゙˙"],
  "ji": ["ジ"],
  "ju": ["ズ"],
  "je": ["ゼ"],
  "jo": ["ゾ"],
  "k": ["", "ㇰ"],
  "kk": ["", "ㇰ˙"],
  "ka": ["カ"],
  "ki": ["キ"],
  "ku": ["ク"],
  "ke": ["ケ"],
  "ko": ["コ"],
  "kha": ["カ̣"],
  "khi": ["キ̣"],
  "khu": ["ク̣"],
  "khe": ["ケ̣"],
  "kho": ["コ̣"],
  "l": ["", "ㇽ"],
  "ll": ["", "ㇽ˙"],
  "la": ["ラ"],
  "li": ["リ"],
  "lu": ["ル"],
  "le": ["レ"],
  "lo": ["ロ"],
  "m": ["ム", "ㇺ"],
  "ma": ["マ"],
  "mi": ["ミ"],
  "mu": ["ム"],
  "me": ["メ"],
  "mo": ["モ"],
  "n": ["", "ㇴ"],
  "nn": ["", "~"],
  "na": ["ナ"],
  "ni": ["ニ"],
  "nu": ["ヌ"],
  "ne": ["ネ"],
  "no": ["ノ"],
  "ng": ["ㆁ", "ᇰ"],
  "nga": ["カ゚"],
  "ngi": ["キ゚"],
  "ngu": ["ク゚"],
  "nge": ["ケ゚"],
  "ngo": ["コ゚"],
  "o": ["オ", "ォ"],
  "or": ["オ̅", "ォ̅"],
  "p": ["", "ㇷ゚"],
  "pp": ["", "ㇷ゚˙"],
  "pa": ["パ"],
  "pi": ["ピ"],
  "pu": ["プ"],
  "pe": ["ペ"],
  "po": ["ポ"],
  "pha": ["パ̣"],
  "phi": ["ピ̣"],
  "phu": ["プ̣"],
  "phe": ["ペ̣"],
  "pho": ["ポ̣"],
  "s": ["", "ㇲ"],
  "ss": ["", "ㇲ˙"],
  "sa": ["サ"],
  "si": ["シ"],
  "su": ["ス"],
  "se": ["セ"],
  "so": ["ソ"],
  "t": ["", "ッ"],
  "tt": ["", "ッ˙"],
  "ta": ["タ"],
  "ti": ["チ̅"],
  "tu": ["ツ̅"],
  "te": ["テ"],
  "to": ["ト"],
  "tha": ["タ̣"],
  "thi": ["チ̣̅"],
  "thu": ["ツ̣̅"],
  "the": ["テ̣"],
  "tho": ["ト̣"],
  "u": ["ウ", "ゥ"],
  "ur": ["ㅗ", "ᅩ"],
  "w": ["˪", "˪~"],
  "x": ["ˊ", "ˊ~"],
  "y": ["ˋ", "ˋ~"],
  "z": ["˫", "˫~"]
}
